convert_ej/convert.py
convert_ej/problem.py
convert_ej/readers.py
convert_ej/writers.py
convert_ej/templates/BOCA/compare/c
convert_ej/templates/BOCA/compare/checker-boca
convert_ej/templates/BOCA/compare/cpp
convert_ej/templates/BOCA/compare/java
convert_ej/templates/BOCA/compare/py2
convert_ej/templates/BOCA/compare/py3
convert_ej/templates/BOCA/compile/c
convert_ej/templates/BOCA/compile/cpp
convert_ej/templates/BOCA/compile/java
convert_ej/templates/BOCA/compile/py2
convert_ej/templates/BOCA/compile/py3
convert_ej/templates/BOCA/limits/c
convert_ej/templates/BOCA/limits/cpp
convert_ej/templates/BOCA/limits/java
convert_ej/templates/BOCA/limits/py2
convert_ej/templates/BOCA/limits/py3
convert_ej/templates/BOCA/run/c
convert_ej/templates/BOCA/run/cpp
convert_ej/templates/BOCA/run/java
convert_ej/templates/BOCA/run/py2
convert_ej/templates/BOCA/run/py3
convert_ej/templates/BOCA/tex/boca.cls
convert_ej/templates/BOCA/tex/main.tex
convert_ej/templates/CodeRunner/problem.xml
convert_ej/templates/CodeRunner/test.xml
convert_ej-1.1.7.dist-info/LICENSE
convert_ej-1.1.7.dist-info/METADATA
convert_ej-1.1.7.dist-info/WHEEL
convert_ej-1.1.7.dist-info/entry_points.txt
convert_ej-1.1.7.dist-info/top_level.txt
convert_ej-1.1.7.dist-info/RECORD
