Metadata-Version: 2.1
Name: convert-ej
Version: 1.1.7
Summary: A software tool for converting problem files between electronic judges formats.
Home-page: https://github.com/gnramos/convert-ej
Author: Tiago de Souza Fernandes
Author-email: tiagotsf2000@gmail.com
License: GNU GENERAL PUBLIC LICENSE
Platform: UNKNOWN
Classifier: License :: OSI Approved :: GNU General Public License v3 or later (GPLv3+)
Classifier: Programming Language :: Python :: 3.7
